rmw/_dummy.cpython-312-x86_64-linux-gnu.so
ros_rmw-7.8.2.data/data/include/rmw/rmw/allocators.h
ros_rmw-7.8.2.data/data/include/rmw/rmw/check_type_identifiers_match.h
ros_rmw-7.8.2.data/data/include/rmw/rmw/convert_rcutils_ret_to_rmw_ret.h
ros_rmw-7.8.2.data/data/include/rmw/rmw/discovery_options.h
ros_rmw-7.8.2.data/data/include/rmw/rmw/domain_id.h
ros_rmw-7.8.2.data/data/include/rmw/rmw/dynamic_message_type_support.h
ros_rmw-7.8.2.data/data/include/rmw/rmw/enclave.h
ros_rmw-7.8.2.data/data/include/rmw/rmw/error_handling.h
ros_rmw-7.8.2.data/data/include/rmw/rmw/event.h
ros_rmw-7.8.2.data/data/include/rmw/rmw/event_callback_type.h
ros_rmw-7.8.2.data/data/include/rmw/rmw/features.h
ros_rmw-7.8.2.data/data/include/rmw/rmw/get_network_flow_endpoints.h
ros_rmw-7.8.2.data/data/include/rmw/rmw/get_node_info_and_types.h
ros_rmw-7.8.2.data/data/include/rmw/rmw/get_service_names_and_types.h
ros_rmw-7.8.2.data/data/include/rmw/rmw/get_topic_endpoint_info.h
ros_rmw-7.8.2.data/data/include/rmw/rmw/get_topic_names_and_types.h
ros_rmw-7.8.2.data/data/include/rmw/rmw/incompatible_qos_events_statuses.h
ros_rmw-7.8.2.data/data/include/rmw/rmw/init.h
ros_rmw-7.8.2.data/data/include/rmw/rmw/init_options.h
ros_rmw-7.8.2.data/data/include/rmw/rmw/macros.h
ros_rmw-7.8.2.data/data/include/rmw/rmw/message_sequence.h
ros_rmw-7.8.2.data/data/include/rmw/rmw/names_and_types.h
ros_rmw-7.8.2.data/data/include/rmw/rmw/network_flow_endpoint.h
ros_rmw-7.8.2.data/data/include/rmw/rmw/network_flow_endpoint_array.h
ros_rmw-7.8.2.data/data/include/rmw/rmw/publisher_options.h
ros_rmw-7.8.2.data/data/include/rmw/rmw/qos_policy_kind.h
ros_rmw-7.8.2.data/data/include/rmw/rmw/qos_profiles.h
ros_rmw-7.8.2.data/data/include/rmw/rmw/qos_string_conversions.h
ros_rmw-7.8.2.data/data/include/rmw/rmw/ret_types.h
ros_rmw-7.8.2.data/data/include/rmw/rmw/rmw.h
ros_rmw-7.8.2.data/data/include/rmw/rmw/sanity_checks.h
ros_rmw-7.8.2.data/data/include/rmw/rmw/security_options.h
ros_rmw-7.8.2.dist-info/METADATA
ros_rmw-7.8.2.dist-info/WHEEL
ros_rmw-7.8.2.dist-info/top_level.txt
ros_rmw-7.8.2.dist-info/RECORD
