Metadata-Version: 2.4
Name: ros-rmw
Version: 7.8.2
Summary: A ROS 2 package providing the RMW interface, an abstraction layer for DDS implementations to communicate with the ROS 2 Client Library.
Requires-Dist: ros-rosidl-dynamic-typesupport~=0.3.1
Requires-Dist: ros-rcutils~=6.9.8
Requires-Dist: ros-rosidl-runtime-c~=4.9.5
Dynamic: description
Dynamic: description-content-type
Dynamic: requires-dist
Dynamic: summary
